hunter_how/__init__.py
hunter_how/api_key.py
hunter_how/main.py
hunter_how/parse.py
hunter_how/search.py
hunter_how_cli-1.0.1.dist-info/licenses/LICENSE
hunter_how_cli-1.0.1.dist-info/METADATA
hunter_how_cli-1.0.1.dist-info/WHEEL
hunter_how_cli-1.0.1.dist-info/entry_points.txt
hunter_how_cli-1.0.1.dist-info/top_level.txt
hunter_how_cli-1.0.1.dist-info/RECORD
