Metadata-Version: 2.4
Name: hunter-how-cli
Version: 1.0.1
Summary: CLI tool for interacting with the hunter.how search engine
Author-email: Daniil Kadochnikov <daniil.kadochnikov@proton.me>
License: This is free and unencumbered software released into the public domain.
Project-URL: Homepage, https://github.com/anti79/hunter-how-cli
Requires-Python: >=3.8
License-File: LICENSE
Requires-Dist: requests
Requires-Dist: platformdirs
Dynamic: license-file
